LICENSE.md
README.md
pyproject.toml
netbox_diode_plugin/__init__.py
netbox_diode_plugin/client.py
netbox_diode_plugin/forms.py
netbox_diode_plugin/models.py
netbox_diode_plugin/navigation.py
netbox_diode_plugin/plugin_config.py
netbox_diode_plugin/tables.py
netbox_diode_plugin/urls.py
netbox_diode_plugin/version.py
netbox_diode_plugin/views.py
netbox_diode_plugin/api/__init__.py
netbox_diode_plugin/api/applier.py
netbox_diode_plugin/api/authentication.py
netbox_diode_plugin/api/common.py
netbox_diode_plugin/api/compat.py
netbox_diode_plugin/api/differ.py
netbox_diode_plugin/api/matcher.py
netbox_diode_plugin/api/permissions.py
netbox_diode_plugin/api/plugin_utils.py
netbox_diode_plugin/api/serializers.py
netbox_diode_plugin/api/supported_models.py
netbox_diode_plugin/api/transformer.py
netbox_diode_plugin/api/urls.py
netbox_diode_plugin/api/views.py
netbox_diode_plugin/diode/clients.py
netbox_diode_plugin/management/__init__.py
netbox_diode_plugin/management/commands/__init__.py
netbox_diode_plugin/management/commands/generate_matching_docs.py
netbox_diode_plugin/migrations/0001_squashed_0005.py
netbox_diode_plugin/migrations/0006_clientcredentials_alter_setting_diode_target.py
netbox_diode_plugin/migrations/0007_setting_model_cleanup.py
netbox_diode_plugin/migrations/0008_setting_branch.py
netbox_diode_plugin/migrations/__init__.py
netbox_diode_plugin/templates/diode/client_credential_add.html
netbox_diode_plugin/templates/diode/client_credential_delete.html
netbox_diode_plugin/templates/diode/client_credential_list.html
netbox_diode_plugin/templates/diode/client_credential_secret.html
netbox_diode_plugin/templates/diode/settings.html
netbox_diode_plugin/templates/diode/settings_edit.html
netbox_diode_plugin/templates/diode/htmx/delete_form.html
netboxlabs_diode_netbox_plugin.egg-info/PKG-INFO
netboxlabs_diode_netbox_plugin.egg-info/SOURCES.txt
netboxlabs_diode_netbox_plugin.egg-info/dependency_links.txt
netboxlabs_diode_netbox_plugin.egg-info/requires.txt
netboxlabs_diode_netbox_plugin.egg-info/top_level.txt