Metadata-Version: 2.4
Name: netboxlabs-diode-netbox-plugin
Version: 1.7.0
Summary: NetBox Labs, Diode NetBox plugin
Author-email: NetBox Labs <support@netboxlabs.com>
Maintainer-email: NetBox Labs <support@netboxlabs.com>
License: NetBox Limited Use License 1.0
Project-URL: Homepage, https://netboxlabs.com/
Classifier: Development Status :: 4 - Beta
Classifier: Intended Audience :: Developers
Classifier: Topic :: Software Development :: Build Tools
Classifier: Programming Language :: Python :: 3
Classifier: Programming Language :: Python :: 3 :: Only
Classifier: Programming Language :: Python :: 3.10
Classifier: Programming Language :: Python :: 3.11
Classifier: Programming Language :: Python :: 3.12
Classifier: Programming Language :: Python :: 3.13
Requires-Python: >=3.10
License-File: LICENSE.md
Requires-Dist: Brotli>=1.1.0
Requires-Dist: certifi>=2024.7.4
Requires-Dist: grpcio>=1.68.1
Requires-Dist: protobuf>=5.28.1
Provides-Extra: dev
Requires-Dist: black; extra == "dev"
Requires-Dist: check-manifest; extra == "dev"
Requires-Dist: ruff; extra == "dev"
Provides-Extra: test
Requires-Dist: coverage; extra == "test"
Requires-Dist: pytest; extra == "test"
Requires-Dist: pytest-cov; extra == "test"
Dynamic: license-file
